literature_mapper/__init__.py
literature_mapper/agents.py
literature_mapper/ai_prompts.py
literature_mapper/analysis.py
literature_mapper/arxiv_api.py
literature_mapper/cli.py
literature_mapper/config.py
literature_mapper/database.py
literature_mapper/embeddings.py
literature_mapper/exceptions.py
literature_mapper/ghosts.py
literature_mapper/logging_config.py
literature_mapper/mapper.py
literature_mapper/openalex.py
literature_mapper/retrieval.py
literature_mapper/temporal.py
literature_mapper/validation.py
literature_mapper/viz.py
literature_mapper-2.1.6.dist-info/METADATA
literature_mapper-2.1.6.dist-info/WHEEL
literature_mapper-2.1.6.dist-info/entry_points.txt
literature_mapper-2.1.6.dist-info/top_level.txt
literature_mapper-2.1.6.dist-info/RECORD
