Metadata-Version: 2.4
Name: literature-mapper
Version: 2.1.6
Summary: AI-powered Python library for systematic, scalable analysis of academic literature
Author-email: Jeremiah Bohr <bohrj@uwosh.edu>
Project-URL: Homepage, https://github.com/jeremiahbohr/literature-mapper
Project-URL: Repository, https://github.com/jeremiahbohr/literature-mapper.git
Project-URL: Issues, https://github.com/jeremiahbohr/literature-mapper/issues
Keywords: academic,literature,analysis,ai,research,pdf
Classifier: Development Status :: 4 - Beta
Classifier: Intended Audience :: Science/Research
Classifier: License :: OSI Approved :: MIT License
Classifier: Operating System :: OS Independent
Classifier: Programming Language :: Python :: 3
Classifier: Programming Language :: Python :: 3.10
Classifier: Programming Language :: Python :: 3.11
Classifier: Programming Language :: Python :: 3.12
Classifier: Topic :: Scientific/Engineering :: Information Analysis
Requires-Python: >=3.10
Requires-Dist: google-generativeai>=0.7.0
Requires-Dist: pandas>=1.5.0
Requires-Dist: sqlalchemy>=2.0.0
Requires-Dist: pypdf>=4.0.0
Requires-Dist: typer>=0.9.0
Requires-Dist: rich>=13.0.0
Requires-Dist: tqdm>=4.64.0
Requires-Dist: numpy>=1.20.0
Provides-Extra: dev
Requires-Dist: pytest>=7.0.0; extra == "dev"
Requires-Dist: pytest-cov>=4.0.0; extra == "dev"
Requires-Dist: black>=23.0.0; extra == "dev"
Requires-Dist: isort>=5.12.0; extra == "dev"
Requires-Dist: mypy>=1.0.0; extra == "dev"
